multipart/steram/main.py
aio_multipart-0.1.1a0.dist-info/METADATA
aio_multipart-0.1.1a0.dist-info/WHEEL
aio_multipart-0.1.1a0.dist-info/RECORD
